onesentence/__init__.py
onesentence/analyze.py
onesentence/cli.py
onesentence-0.0.3.dist-info/licenses/LICENSE
onesentence-0.0.3.dist-info/METADATA
onesentence-0.0.3.dist-info/WHEEL
onesentence-0.0.3.dist-info/entry_points.txt
onesentence-0.0.3.dist-info/top_level.txt
onesentence-0.0.3.dist-info/RECORD
