Metadata-Version: 2.4
Name: onesentence
Version: 0.0.3
Summary: A Pre-commit hook for 'one sentence per line' documentation practices.
Classifier: Programming Language :: Python :: 3 :: Only
Classifier: Programming Language :: Python :: 3.9
Classifier: Programming Language :: Python :: 3.10
Classifier: Programming Language :: Python :: 3.11
Classifier: Programming Language :: Python :: 3.12
Classifier: Programming Language :: Python :: 3.13
Requires-Python: >=3.9
License-File: LICENSE
Requires-Dist: fire>=0.7
Requires-Dist: pysbd>=0.3.4
Dynamic: license-file
